RippleCarryCounter4/D_FF.v
// D flip flop
module D_FF(d, q, clk, reset);
input d, clk, reset;
output q;
reg q;

	always @(posedge reset or negedge clk) begin
		if (reset) begin
			q = 1'b0; // reset
		end
			
		else
			q = d;
	end

endmodule

RippleCarryCounter4/T_FF.v
// T flip flop
`include "D_FF.v"
module T_FF(q, clk, reset);
input clk, reset;
output q;
wire d;
	D_FF dff (d, q, clk, reset);
	not n1 (d, q); /* The output q connects to the input d 
					  through a not gate. */
endmodule

RippleCarryCounter4/RCC4.v
// 4 bits ripple carry counter
`include "T_FF.v"
module RCC4(q, clk, reset);
input clk, reset;
output [3:0] q;

	T_FF tff0 (q[0], clk, reset);
	T_FF tff1 (q[1], q[0], reset);
	T_FF tff2 (q[2], q[1], reset);
	T_FF tff3 (q[3], q[2], reset);

endmodule

RippleCarryCounter4/RCC4_test.v
// 4 bit ripple carry counter test bench
`timescale 1ns/100ps
`include "RCC4.v"
module RCC4_test;
reg clk, reset;
wire [3:0] q;

	RCC4 rcc (q, clk, reset);

	initial begin
		reset = 1; // reset at the beginning.
		clk = 0;
		$dumpfile("RCC4_test.vcd");
		$dumpvars;
	end


	always
		#5 clk = ~clk;

	always @(negedge clk) begin

		#10 reset = 0;
		#200 $finish;
	end
	
endmodule

RippleCarryCounter4/RCC4_test.vcd
$date
	Tue Feb 21 13:01:27 2017
$end
$version
	Icarus Verilog
$end
$timescale
	100ps
$end
$scope module RCC4_test $end
$var wire 4 ! q [3:0] $end
$var reg 1 " clk $end
$var reg 1 # reset $end
$scope module rcc $end
$var wire 1 $ clk $end
$var wire 4 % q [3:0] $end
$var wire 1 & reset $end
$scope module tff0 $end
$var wire 1 $ clk $end
$var wire 1 ' d $end
$var wire 1 ( q $end
$var wire 1 & reset $end
$scope module dff $end
$var wire 1 $ clk $end
$var wire 1 ' d $end
$var wire 1 & reset $end
$var reg 1 ) q $end
$upscope $end
$upscope $end
$scope module tff1 $end
$var wire 1 * clk $end
$var wire 1 + d $end
$var wire 1 , q $end
$var wire 1 & reset $end
$scope module dff $end
$var wire 1 * clk $end
$var wire 1 + d $end
$var wire 1 & reset $end
$var reg 1 - q $end
$upscope $end
$upscope $end
$scope module tff2 $end
$var wire 1 . clk $end
$var wire 1 / d $end
$var wire 1 0 q $end
$var wire 1 & reset $end
$scope module dff $end
$var wire 1 . clk $end
$var wire 1 / d $end
$var wire 1 & reset $end
$var reg 1 1 q $end
$upscope $end
$upscope $end
$scope module tff3 $end
$var wire 1 2 clk $end
$var wire 1 3 d $end
$var wire 1 4 q $end
$var wire 1 & reset $end
$scope module dff $end
$var wire 1 2 clk $end
$var wire 1 3 d $end
$var wire 1 & reset $end
$var reg 1 5 q $end
$upscope $end
$upscope $end
$upscope $end
$upscope $end
$enddefinitions $end
#0
$dumpvars
05
04
13
02
01
00
1/
0.
0-
0,
1+
0*
0)
0(
1'
1&
b0 %
0$
1#
0"
b0 !
$end
#50
1"
1$
#100
0"
0$
#150
1"
1$
#200
0'
1*
1)
1(
b1 !
b1 %
0"
0$
0#
0&
#250
1"
1$
#300
0+
1.
1-
1,
1'
0*
0)
0(
b10 !
b10 %
0"
0$
#350
1"
1$
#400
0'
1*
1)
1(
b11 !
b11 %
0"
0$
#450
1"
1$
#500
0/
12
11
10
1+
0.
0-
0,
1'
0*
0)
0(
b100 !
b100 %
0"
0$
#550
1"
1$
#600
0'
1*
1)
1(
b101 !
b101 %
0"
0$
#650
1"
1$
#700
0+
1.
1-
1,
1'
0*
0)
0(
b110 !
b110 %
0"
0$
#750
1"
1$
#800
0'
1*
1)
1(
b111 !
b111 %
0"
0$
#850
1"
1$
#900
03
15
14
1/
02
01
00
1+
0.
0-
0,
1'
0*
0)
0(
b1000 !
b1000 %
0"
0$
#950
1"
1$
#1000
0'
1*
1)
1(
b1001 !
b1001 %
0"
0$
#1050
1"
1$
#1100
0+
1.
1-
1,
1'
0*
0)
0(
b1010 !
b1010 %
0"
0$
#1150
1"
1$
#1200
0'
1*
1)
1(
b1011 !
b1011 %
0"
0$
#1250
1"
1$
#1300
0/
12
11
10
1+
0.
0-
0,
1'
0*
0)
0(
b1100 !
b1100 %
0"
0$
#1350
1"
1$
#1400
0'
1*
1)
1(
b1101 !
b1101 %
0"
0$
#1450
1"
1$
#1500
0+
1.
1-
1,
1'
0*
0)
0(
b1110 !
b1110 %
0"
0$
#1550
1"
1$
#1600
0'
1*
1)
1(
b1111 !
b1111 %
0"
0$
#1650
1"
1$
#1700
13
05
04
1/
02
01
00
1+
0.
0-
0,
1'
0*
0)
0(
b0 !
b0 %
0"
0$
#1750
1"
1$
#1800
0'
1*
1)
1(
b1 !
b1 %
0"
0$
#1850
1"
1$
#1900
0+
1.
1-
1,
1'
0*
0)
0(
b10 !
b10 %
0"
0$
#1950
1"
1$
#2000
0'
1*
1)
1(
b11 !
b11 %
0"
0$
#2050
1"
1$
#2100
0/
12
11
10
1+
0.
0-
0,
1'
0*
0)
0(
b100 !
b100 %
0"
0$
#2150
1"
1$
#2200
0'
1*
1)
1(
b101 !
b101 %
0"
0$
