multiplexer/mux21.v
// use tristate buffer to build a 2 to 1 mux.
module mux21(in0, in1, s, out);
input in0, in1, s;
output out;


	bufif1(out, in1, s);
	bufif0(out, in0, s);

endmodule

multiplexer/mux81.v
// use 2 to 1 mux to build a 8 to 1 mux.
`include "mux21.v"

module mux81(in, s, out);
input [7:0] in;
input [2:0] s;
output out;
wire [3:0] stage1;
wire [1:0] stage2;
	
	mux21 mux1(in[0], in[1], s[0], stage1[0]);
	mux21 mux2(in[2], in[3], s[0], stage1[1]);
	mux21 mux3(in[4], in[5], s[0], stage1[2]);
	mux21 mux4(in[6], in[7], s[0], stage1[3]);
	mux21 mux5(stage1[0], stage1[1], s[1], stage2[0]);
	mux21 mux6(stage1[2], stage1[3], s[1], stage2[1]);
	mux21 mux7(stage2[0], stage2[1], s[2], out);

endmodule

multiplexer/mux81_test.v
// 2 to 1 mux test bench.
`timescale 10ns/1ns
`include "mux81.v"

module mux81_test;
reg [7:0] in;
reg [2:0] s;

	mux81 mux (in, s, out);

	initial begin
		in = 1;
		$dumpfile("mux81_test.vcd");
		$dumpvars;
	end

	always begin
		#1 s = 0;
		#1 in = 0;
		#1 in = 2;
		#1 s = 1;
		#1 in = 4;
		#1 s = 2;
		#1 in = 8;
		#1 s = 3;
		#1 in = 16;
		#1 s = 4;
		#1 $finish;
	end
endmodule

multiplexer/mux81_test.vcd
$date
	Tue May 23 19:00:36 2017
$end
$version
	Icarus Verilog
$end
$timescale
	1ns
$end
$scope module mux81_test $end
$var wire 1 ! out $end
$var reg 8 " in [7:0] $end
$var reg 3 # s [2:0] $end
$scope module mux $end
$var wire 8 $ in [7:0] $end
$var wire 1 ! out $end
$var wire 3 % s [2:0] $end
$var wire 4 & stage1 [3:0] $end
$var wire 2 ' stage2 [1:0] $end
$scope module mux1 $end
$var wire 1 ( in0 $end
$var wire 1 ) in1 $end
$var wire 1 * out $end
$var wire 1 + s $end
$upscope $end
$scope module mux2 $end
$var wire 1 , in0 $end
$var wire 1 - in1 $end
$var wire 1 . out $end
$var wire 1 / s $end
$upscope $end
$scope module mux3 $end
$var wire 1 0 in0 $end
$var wire 1 1 in1 $end
$var wire 1 2 out $end
$var wire 1 3 s $end
$upscope $end
$scope module mux4 $end
$var wire 1 4 in0 $end
$var wire 1 5 in1 $end
$var wire 1 6 out $end
$var wire 1 7 s $end
$upscope $end
$scope module mux5 $end
$var wire 1 8 in0 $end
$var wire 1 9 in1 $end
$var wire 1 : out $end
$var wire 1 ; s $end
$upscope $end
$scope module mux6 $end
$var wire 1 < in0 $end
$var wire 1 = in1 $end
$var wire 1 > out $end
$var wire 1 ? s $end
$upscope $end
$scope module mux7 $end
$var wire 1 @ in0 $end
$var wire 1 A in1 $end
$var wire 1 ! out $end
$var wire 1 B s $end
$upscope $end
$upscope $end
$upscope $end
$enddefinitions $end
#0
$dumpvars
xB
xA
x@
x?
x>
x=
x<
x;
x:
x9
x8
x7
x6
05
04
x3
x2
01
00
x/
x.
0-
0,
x+
x*
0)
1(
bx '
bx &
bx %
b1 $
bx #
b1 "
x!
$end
#10
1!
1@
0A
1:
18
09
b1 '
0>
0<
0=
1*
0+
0.
0/
02
03
b1 &
06
07
0;
0?
0B
b0 #
b0 %
#20
0!
0@
b0 '
0:
08
b0 &
0*
0(
b0 "
b0 $
#30
1)
b10 "
b10 $
#40
1!
1@
b1 '
1:
18
1*
1+
0.
1/
02
13
b1 &
06
17
b1 #
b1 %
#50
0!
0@
b0 '
0:
08
b0 &
0*
0)
1,
b100 "
b100 $
#60
1!
1@
19
0+
b10 &
1.
0/
03
07
1:
1;
b1 '
0>
1?
b10 #
b10 %
#70
0!
0@
b0 '
0:
09
b0 &
0.
0,
1-
b1000 "
b1000 $
#80
1!
1@
b1 '
1:
19
0*
1+
1.
1/
02
13
b10 &
06
17
b11 #
b11 %
#90
0!
0@
b0 '
0:
09
b0 &
0.
0-
10
b10000 "
b10000 $
#100
1A
b10 '
1>
1<
0+
0/
b100 &
12
03
07
0;
0?
1!
1B
b100 #
b100 %
